tree_sitter_zig/__init__.py
tree_sitter_zig/__init__.pyi
tree_sitter_zig/_binding.pyd
tree_sitter_zig/binding.c
tree_sitter_zig/py.typed
tree_sitter_zig/queries/folds.scm
tree_sitter_zig/queries/highlights.scm
tree_sitter_zig/queries/indents.scm
tree_sitter_zig/queries/injections.scm
tree_sitter_zig-1.1.0.dist-info/LICENSE
tree_sitter_zig-1.1.0.dist-info/METADATA
tree_sitter_zig-1.1.0.dist-info/WHEEL
tree_sitter_zig-1.1.0.dist-info/top_level.txt
tree_sitter_zig-1.1.0.dist-info/RECORD
